CHANGELOG.md
README.md
monkeyevents/__init__.py
monkeyevents/abstract_agent_event.py
monkeyevents/agent_shutdown_event.py
monkeyevents/cpu_consumption_event.py
monkeyevents/credentials_stolen_event.py
monkeyevents/defacement_event.py
monkeyevents/exploitation_event.py
monkeyevents/file_encryption_event.py
monkeyevents/fingerprinting_event.py
monkeyevents/hostname_discovery_event.py
monkeyevents/http_request_event.py
monkeyevents/i_agent_event_serializer.py
monkeyevents/os_discovery_event.py
monkeyevents/password_restoration_event.py
monkeyevents/ping_scan_event.py
monkeyevents/propagation_event.py
monkeyevents/py.typed
monkeyevents/pydantic_agent_event_serializer.py
monkeyevents/ram_consumption_event.py
monkeyevents/schema.py
monkeyevents/tags/__init__.py
monkeyevents/tags/attack.py
monkeyevents/tcp_scan_event.py
monkeyevents-0.4.0.dist-info/LICENSE
monkeyevents-0.4.0.dist-info/METADATA
monkeyevents-0.4.0.dist-info/WHEEL
monkeyevents-0.4.0.dist-info/RECORD
